{
  "identificacao": {
    "id": "haruki-kawasaki",
    "nome": "Haruki Kawasaki",
    "nomeCompleto": "",
    "apelido": "",
    "foto": "dados/images/players/brasil/haruki-kawasaki.png",
    "clubeAtual": "remo",
    "nacionalidade": [
      "japao"
    ],
    "dataNascimento": "08/04/2010",
    "idade": 16,
    "altura": "",
    "peso": "",
    "pePreferido": "",
    "numero": "35"
  },
  "posicao": {
    "principal": "Defender",
    "secundarias": []
  },
  "contratoMercado": {
    "valorMercado": "-",
    "salario": "",
    "contratoAte": "",
    "multaRescisoria": "",
    "empresario": "",
    "statusTransferencia": ""
  },
  "overall": {
    "overall": 58,
    "potencial": 70,
    "reputacao": 58,
    "potencialMidia": 75
  },
  "tecnicos": {
    "finalizacao": 52,
    "chuteLongo": 52,
    "passeCurto": 59,
    "passeLongo": 60,
    "visao": 57,
    "cruzamento": 52,
    "drible": 52,
    "controleBola": 58,
    "dominio": 52,
    "curva": 52,
    "cobrancaFalta": 52,
    "penalti": 52,
    "cabecamento": 52,
    "voleio": 52,
    "acrobacia": 52
  },
  "fisicos": {
    "velocidade": 54,
    "aceleracao": 54,
    "explosao": 54,
    "agilidade": 54,
    "equilibrio": 54,
    "resistencia": 61,
    "forca": 54,
    "impulsao": 54,
    "stamina": 63
  },
  "defensivos": {
    "marcacao": 50,
    "desarme": 50,
    "interceptacao": 50,
    "posicionamentoDefensivo": 50,
    "pressao": 58,
    "cobertura": 50,
    "empenhoTatico": 63
  },
  "mentais": {
    "inteligencia": 59,
    "criatividade": 55,
    "decisao": 59,
    "visaoJogo": 55,
    "compostura": 56,
    "frieza": 54,
    "concentracao": 59,
    "regularidade": 54,
    "ansiedade": 42,
    "agressividade": 55,
    "coragem": 55,
    "lideranca": 53,
    "trabalhoEquipe": 57
  },
  "personalidade": {
    "ego": 50,
    "ambicao": 79,
    "profissionalismo": 63,
    "lealdade": 64,
    "catimba": 55,
    "violencia": 32,
    "disciplina": 74,
    "adaptacao": 55
  },
  "especial": {
    "estrela": 47,
    "jogoGrande": 48,
    "momentoHeroico": 48,
    "supersub": 45,
    "decisivo": 53,
    "provocador": 37,
    "batedorPenaltis": 52,
    "cobradorFalta": 52,
    "especialistaEscanteio": 50
  },
  "goleiro": {
    "reflexos": 10,
    "defesa": 10,
    "posicionamentoGol": 10,
    "saidaGol": 10,
    "jogoPes": 10,
    "reposicao": 10,
    "pegadorPenaltis": 10
  },
  "statusDinamico": {
    "moral": 70,
    "fadiga": 0,
    "ritmoDeJogo": 45,
    "confianca": 50,
    "formaAtual": 50,
    "lesionado": false,
    "suspenso": false,
    "minutagemTemporada": 0
  },
  "historico": {
    "jogos": 0,
    "gols": 0,
    "assistencias": 0,
    "cartoesAmarelos": 0,
    "cartoesVermelhos": 0,
    "titulos": [],
    "premiosIndividuais": []
  },
  "desenvolvimento": {
    "evolucaoEsperada": 12,
    "tetoEvolucao": 70,
    "decadenciaFisica": 0,
    "idadePico": "27-30"
  },
  "iaGameplay": {
    "tendenciaDrible": 44,
    "tendenciaChute": 44,
    "tendenciaPasse": 58,
    "tendenciaMarcacao": 54,
    "movimentacaoOfensiva": 58,
    "recomposicao": 63,
    "participacaoJogo": 59,
    "intensidade": 60,
    "riscoCriativo": 55
  },
  "fonte": {
    "transfermarktUrl": "https://www.transfermarkt.com/haruki-kawasaki/profil/spieler/1541595",
    "coletadoEm": "2026-05-16"
  },
  "referencias": {
    "clube": "dados/clubs/brasil/remo.json",
    "nacionalidade": [
      "dados/selecoes/paises/japao.json"
    ],
    "foto": "dados/images/players/brasil/haruki-kawasaki.png",
    "ligasNacionais": "dados/ligas/brasil",
    "competicoesInternacionais": "dados/intenational-competitions",
    "competicoesSelecoes": "dados/selecoes/competition",
    "historicoClubes": "dados/ligas/(pais-da-conquista)",
    "historicoInternacional": "dados/intenational-competitions",
    "historicoSelecoes": "dados/selecoes/competition"
  }
}