{
  "identificacao": {
    "id": "thiago-mendes",
    "nome": "Thiago Mendes",
    "nomeCompleto": "",
    "apelido": "",
    "foto": "dados/images/players/brasil/thiago-mendes.png",
    "clubeAtual": "vasco-da-gama",
    "nacionalidade": [
      "brasil"
    ],
    "dataNascimento": "15/03/1992",
    "idade": 34,
    "altura": "",
    "peso": "",
    "pePreferido": "",
    "numero": "23"
  },
  "posicao": {
    "principal": "Volante",
    "secundarias": []
  },
  "contratoMercado": {
    "valorMercado": "€1.50m",
    "salario": "",
    "contratoAte": "",
    "multaRescisoria": "",
    "empresario": "",
    "statusTransferencia": ""
  },
  "overall": {
    "overall": 66,
    "potencial": 66,
    "reputacao": 66,
    "potencialMidia": 66
  },
  "tecnicos": {
    "finalizacao": 60,
    "chuteLongo": 60,
    "passeCurto": 70,
    "passeLongo": 69,
    "visao": 64,
    "cruzamento": 60,
    "drible": 60,
    "controleBola": 60,
    "dominio": 60,
    "curva": 60,
    "cobrancaFalta": 60,
    "penalti": 60,
    "cabecamento": 60,
    "voleio": 60,
    "acrobacia": 60
  },
  "fisicos": {
    "velocidade": 62,
    "aceleracao": 62,
    "explosao": 62,
    "agilidade": 62,
    "equilibrio": 62,
    "resistencia": 66,
    "forca": 69,
    "impulsao": 62,
    "stamina": 62
  },
  "defensivos": {
    "marcacao": 70,
    "desarme": 71,
    "interceptacao": 69,
    "posicionamentoDefensivo": 68,
    "pressao": 72,
    "cobertura": 67,
    "empenhoTatico": 66
  },
  "mentais": {
    "inteligencia": 69,
    "criatividade": 63,
    "decisao": 66,
    "visaoJogo": 63,
    "compostura": 63,
    "frieza": 65,
    "concentracao": 65,
    "regularidade": 64,
    "ansiedade": 40,
    "agressividade": 63,
    "coragem": 63,
    "lideranca": 63,
    "trabalhoEquipe": 66
  },
  "personalidade": {
    "ego": 63,
    "ambicao": 64,
    "profissionalismo": 73,
    "lealdade": 62,
    "catimba": 47,
    "violencia": 45,
    "disciplina": 76,
    "adaptacao": 65
  },
  "especial": {
    "estrela": 44,
    "jogoGrande": 49,
    "momentoHeroico": 38,
    "supersub": 47,
    "decisivo": 47,
    "provocador": 51,
    "batedorPenaltis": 60,
    "cobradorFalta": 60,
    "especialistaEscanteio": 57
  },
  "goleiro": {
    "reflexos": 10,
    "defesa": 10,
    "posicionamentoGol": 10,
    "saidaGol": 10,
    "jogoPes": 10,
    "reposicao": 10,
    "pegadorPenaltis": 10
  },
  "statusDinamico": {
    "moral": 70,
    "fadiga": 0,
    "ritmoDeJogo": 46,
    "confianca": 51,
    "formaAtual": 51,
    "lesionado": false,
    "suspenso": false,
    "minutagemTemporada": 0
  },
  "historico": {
    "jogos": 0,
    "gols": 0,
    "assistencias": 0,
    "cartoesAmarelos": 0,
    "cartoesVermelhos": 0,
    "titulos": [],
    "premiosIndividuais": []
  },
  "desenvolvimento": {
    "evolucaoEsperada": 0,
    "tetoEvolucao": 66,
    "decadenciaFisica": 5,
    "idadePico": "27-30"
  },
  "iaGameplay": {
    "tendenciaDrible": 52,
    "tendenciaChute": 52,
    "tendenciaPasse": 67,
    "tendenciaMarcacao": 71,
    "movimentacaoOfensiva": 63,
    "recomposicao": 64,
    "participacaoJogo": 66,
    "intensidade": 69,
    "riscoCriativo": 62
  },
  "fonte": {
    "transfermarktUrl": "https://www.transfermarkt.com/thiago-mendes/profil/spieler/135617",
    "coletadoEm": "2026-05-16"
  },
  "referencias": {
    "clube": "dados/clubs/brasil/vasco-da-gama.json",
    "nacionalidade": [
      "dados/selecoes/paises/brasil.json"
    ],
    "foto": "dados/images/players/brasil/thiago-mendes.png",
    "ligasNacionais": "dados/ligas/brasil",
    "competicoesInternacionais": "dados/intenational-competitions",
    "competicoesSelecoes": "dados/selecoes/competition",
    "historicoClubes": "dados/ligas/(pais-da-conquista)",
    "historicoInternacional": "dados/intenational-competitions",
    "historicoSelecoes": "dados/selecoes/competition"
  }
}